nginxPlusAPI/__init__.py
nginxPlusAPI/Client/Client.py
nginxPlusAPI/Client/__init__.py
nginxPlusAPI/KeyValueStore/KeyValueStore.py
nginxPlusAPI/KeyValueStore/__init__.py
nginxPlusAPI/Upstreams/Upstreams.py
nginxPlusAPI/Upstreams/__init__.py
nginxPlusAPI-0.0.2.dist-info/LICENSE
nginxPlusAPI-0.0.2.dist-info/METADATA
nginxPlusAPI-0.0.2.dist-info/WHEEL
nginxPlusAPI-0.0.2.dist-info/top_level.txt
nginxPlusAPI-0.0.2.dist-info/RECORD
