Metadata-Version: 2.1
Name: nginxPlusAPI
Version: 0.0.2
Summary: Python API Client for NGINX Plus API
Home-page: https://github.com/nginx-architects/python-nginxPlusAPI
Author: James Jones
Author-email: jam.jones@f5.com
License: UNKNOWN
Platform: UNKNOWN
Classifier: Programming Language :: Python :: 3
Classifier: License :: Freely Distributable
Classifier: Operating System :: OS Independent
Requires-Python: >=3.6
